src/control_path.v
module control_path(
    input [5:0] opcode, funct,
    input zero,
    output JBEQ, JJRJAL, JAL, JR, RI, LW, SHIFT, SRL,
    output writeReg, writeMem,
    output reg [2:0] op
);

wire BEQ = opcode == 6'b000100;
wire BNE = opcode == 6'b000101;
wire RTYPE = opcode == 6'b000000;
wire SLL = funct == 6'b000000;
wire SW = opcode == 6'b101011;
wire J = opcode == 6'b000010;
// Это R тип?
assign RI = ~(RTYPE || BEQ || BNE);
// Сдвиг left/right? Сдвиг вообще?
assign SRL = funct == 6'b000010;
assign SHIFT = (RTYPE && SRL) || (RTYPE && SLL);
// Загрузка из памяти?
assign LW = opcode == 6'b100011;
// JAL / JR?
assign JR = RTYPE && funct == 6'b001000;
// BEQ/BNE прыжок
assign JBEQ = (BEQ && zero) || (BNE && ~zero);
// JAL?
assign JAL = (opcode == 6'b000011);
// Любой прямой прыжок
assign JJRJAL = J || JR || JAL;
// Запись в память и в регистровый файл (BEQ BNE SW J JR)
assign writeReg = ~(BEQ || BNE || SW || J || JR);
assign writeMem = SW;

// Выбор операции для ALU
always @(*) begin
    casex({opcode, funct})
    12'b000000_100000: op = 3'd0;
    12'b001000_xxxxxx: op = 3'd0;
    12'b000000_100010: op = 3'd1;
    12'b000100_xxxxxx: op = 3'd1;
    12'b000101_xxxxxx: op = 3'd1;
    12'b000000_100100: op = 3'd2;
    12'b001100_xxxxxx: op = 3'd2;
    12'b000000_100101: op = 3'd3;
    12'b001101_xxxxxx: op = 3'd3;
    12'b000000_100110: op = 3'd4;
    12'b001110_xxxxxx: op = 3'd4;
    default: op = 3'd0;
    endcase
end

endmodule

DATAMEM/datamem.v
// Little Endian
// Побайтная адресация
module datamem(
    input clk, writeMem,
    input [31:0] addr, writeData,
    output [31:0] data
);

initial $readmemb("./_memory/empty.mem", memory);

reg [7:0] memory [0:32*4-1];

assign data = {memory[addr + 3], memory[addr + 2], memory[addr + 1], memory[addr]};

always @(posedge clk)
    if (writeMem) {memory[addr + 3], memory[addr + 2], memory[addr + 1], memory[addr]} <= writeData;

always @(posedge clk) $writememb("./_memory/data.mem", memory);

endmodule

src/ALU/alu.v
module alu(
    input [2:0] op,
    input [31:0] a, b,
    output reg [31:0] c,
    output zero
);

assign zero = ~(|c);

always @(*) begin
    case (op)
        3'd0: c = a + b;
        3'd1: c = a - b;
        3'd2: c = a & b;
        3'd3: c = a | b;
        3'd4: c = a ^ b;
        default: c = a + b; 
    endcase
end

endmodule

REGFILE/regfile.v
// Регистры процессора (32)
// $0 — только для чтения (Константа 0)
module regfile(
    input clk, rst, writeReg,
    input [4:0] ra1, ra2, wa,
    input [31:0] wd,
    output [31:0] rd1, rd2
);

integer i;
reg [31:0] list [0:31];

assign rd1 = list[ra1];
assign rd2 = list[ra2];

always @(posedge clk) begin
    if (rst) for (i = 0; i < 32; i = i+1) begin 
        list[i] <= 32'd0;
    end
    else if (writeReg && wa != 32'd0) list[wa] <= wd;
end

endmodule

CMDMEM/cmdmem.v
// Little Endian
// Побайтная адресация
module cmdmem(
    input [31:0] addr,
    output [31:0] cmd
);

initial $readmemb("./_memory/cmd.mem", memory);

reg [7:0] memory [0:32*4-1];

assign cmd = {memory[addr + 3], memory[addr + 2], memory[addr + 1], memory[addr]};


endmodule

PC/pc.v
// Счетчик команд
module pc(
    input clk, rst,
    input [31:0] nextaddr,
    output reg [31:0] addr
);
    always @(posedge clk) begin
        if (rst) addr <= 32'd0;
        else addr <= nextaddr;
    end
endmodule

data_path.v
/*
JBEQ — Jump относительный (После beq/bne)
JJRJAL — Jump по прямому/псевдопрямому адресу
JAL — Выбор регистра $ra для записи при jal
JR – Выбор адреса для jump'а из регистра
RI – R или I инструкция
LW – Инструкция lw
SHIFT – Инструкиця сдвига
SRL – Выбор сдвига вправо (srl)
writeReg/writeMem – разрешение записи по clk в память
*/
module data_path(
    input clk, rst,
    input JBEQ, JJRJAL, JAL, JR, RI, LW, SHIFT, SRL,
    input writeReg, writeMem,
    input [2:0] op,
    output [5:0] opcode, funct,
    output zero
);

// PC + CMDMEM wires
wire [31:0] nextaddr, addr, cmd;
wire [31:0] addrDirect, addrRelate, addrAdd4;
// REGFILE wires
wire [4:0] wa;
wire [31:0] wd, rd1, rd2;
// ALU + near wires
wire [31:0] b, c;
wire [31:0] shiftRt;
// DATAMEM wires
wire [31:0] addrData, data;


// Выбор частей из шины команды
wire [4:0] rs, rt, rdR, shamt, rdI;
wire [15:0] immd;
wire [25:0] jaddr;
assign  opcode = cmd[31:26],
        rs = cmd[25:21],
        rt = cmd[20:16],
        rdR = cmd[15:11],
        shamt = cmd[10:6],
        funct = cmd[5:0],
        rdI = cmd[20:16],
        immd = cmd[15:0],
        jaddr = cmd[25:0];


// Расширение со знаком immd 16->32
wire [31:0] immd32;
assign immd32 = {{16{immd[15]}}, immd};
// Выбор нужного адреса записи для REGFILE
assign wa = JAL ? 5'd31 : (RI ? rdI : rdR);
// Выбор второго (b) значения ALU + сдвинутый rt 
assign b = RI ? immd32 : rd2;
assign shiftRt = SRL ? rd2 >> shamt : rd2 << shamt;
// Выбор адреса для Data Memory
assign addrData = SHIFT ? shiftRt : c;
// Выбор значения записи для REGFILE
assign wd = LW ? data : addrData;
// Выбор следующей команды для PC
assign addrAdd4 = addr + 4;
assign addrDirect = JR ? rd1 : {addr[31:28], jaddr, 2'b00};
assign addrRelate = JBEQ ? ((immd32 << 2) + addrAdd4) : addrAdd4;
assign nextaddr = JJRJAL ? addrDirect : addrRelate;


pc pc(.clk(clk), .rst(rst), .nextaddr(nextaddr), .addr(addr));
cmdmem cmdmem(.addr(addr), .cmd(cmd));
regfile regfile(.clk(clk), .rst(rst), .writeReg(writeReg),
                .ra1(rs), .ra2(rt), .wa(wa), .wd(wd),
                .rd1(rd1), .rd2(rd2));
alu alu(.op(op), .a(rd1), .b(b), .c(c), .zero(zero));
datamem datamem(.clk(clk), .writeMem(writeMem), .addr(addrData), .writeData(rd2), .data(data));


endmodule

main.v
module main(
    input clk, rst
);

wire JBEQ, JJRJAL, JAL, JR, RI, LW, SHIFT, SRL;
wire writeReg, writeMem;
wire [2:0] op;
wire [5:0] opcode, funct;
wire zero;

data_path data_path(.clk(clk), .rst(rst),
                    .JBEQ(JBEQ), .JJRJAL(JJRJAL), .JAL(JAL), .JR(JR), .RI(RI), .LW(LW), .SHIFT(SHIFT), .SRL(SRL),
                    .writeReg(writeReg), .writeMem(writeMem), .op(op),
                    .opcode(opcode), .funct(funct), .zero(zero));

control_path control_path(  .opcode(opcode), .funct(funct),
                            .zero(zero),
                            .JBEQ(JBEQ), .JJRJAL(JJRJAL), .JAL(JAL), .JR(JR), .RI(RI), .LW(LW), .SHIFT(SHIFT), .SRL(SRL),
                            .writeReg(writeReg), .writeMem(writeMem),
                            .op(op));

endmodule

_test/test_main.v
module test_main();

reg clk, rst;
main testee(.clk(clk), .rst(rst));

initial begin
    $dumpfile("dump.vcd");
    $dumpvars(0, test_main);
end
initial #40 $finish;
initial #0 clk = 0;
initial #0 rst = 1;
initial #2 rst = 0;
always begin
    #1 clk = !clk;
end

endmodule

dump.vcd
$date
	Mon Feb 24 16:19:38 2020
$end
$version
	Icarus Verilog
$end
$timescale
	1s
$end
$scope module test_main $end
$var reg 1 ! clk $end
$var reg 1 " rst $end
$scope module testee $end
$var wire 1 ! clk $end
$var wire 1 " rst $end
$var wire 1 # zero $end
$var wire 1 $ writeReg $end
$var wire 1 % writeMem $end
$var wire 6 & opcode [5:0] $end
$var wire 3 ' op [2:0] $end
$var wire 6 ( funct [5:0] $end
$var wire 1 ) SRL $end
$var wire 1 * SHIFT $end
$var wire 1 + RI $end
$var wire 1 , LW $end
$var wire 1 - JR $end
$var wire 1 . JJRJAL $end
$var wire 1 / JBEQ $end
$var wire 1 0 JAL $end
$scope module control_path $end
$var wire 1 / JBEQ $end
$var wire 1 . JJRJAL $end
$var wire 1 - JR $end
$var wire 1 + RI $end
$var wire 1 * SHIFT $end
$var wire 1 % writeMem $end
$var wire 1 $ writeReg $end
$var wire 1 # zero $end
$var wire 6 1 opcode [5:0] $end
$var wire 6 2 funct [5:0] $end
$var wire 1 3 SW $end
$var wire 1 ) SRL $end
$var wire 1 4 SLL $end
$var wire 1 5 RTYPE $end
$var wire 1 , LW $end
$var wire 1 0 JAL $end
$var wire 1 6 J $end
$var wire 1 7 BNE $end
$var wire 1 8 BEQ $end
$var reg 3 9 op [2:0] $end
$upscope $end
$scope module data_path $end
$var wire 1 0 JAL $end
$var wire 1 / JBEQ $end
$var wire 1 . JJRJAL $end
$var wire 1 - JR $end
$var wire 1 , LW $end
$var wire 1 + RI $end
$var wire 1 * SHIFT $end
$var wire 1 ) SRL $end
$var wire 1 ! clk $end
$var wire 3 : op [2:0] $end
$var wire 1 " rst $end
$var wire 1 % writeMem $end
$var wire 1 $ writeReg $end
$var wire 1 # zero $end
$var wire 32 ; wd [31:0] $end
$var wire 5 < wa [4:0] $end
$var wire 32 = shiftRt [31:0] $end
$var wire 5 > shamt [4:0] $end
$var wire 5 ? rt [4:0] $end
$var wire 5 @ rs [4:0] $end
$var wire 5 A rdR [4:0] $end
$var wire 5 B rdI [4:0] $end
$var wire 32 C rd2 [31:0] $end
$var wire 32 D rd1 [31:0] $end
$var wire 6 E opcode [5:0] $end
$var wire 32 F nextaddr [31:0] $end
$var wire 26 G jaddr [25:0] $end
$var wire 32 H immd32 [31:0] $end
$var wire 16 I immd [15:0] $end
$var wire 6 J funct [5:0] $end
$var wire 32 K data [31:0] $end
$var wire 32 L cmd [31:0] $end
$var wire 32 M c [31:0] $end
$var wire 32 N b [31:0] $end
$var wire 32 O addrRelate [31:0] $end
$var wire 32 P addrDirect [31:0] $end
$var wire 32 Q addrData [31:0] $end
$var wire 32 R addrAdd4 [31:0] $end
$var wire 32 S addr [31:0] $end
$scope module alu $end
$var wire 32 T b [31:0] $end
$var wire 3 U op [2:0] $end
$var wire 1 # zero $end
$var wire 32 V a [31:0] $end
$var reg 32 W c [31:0] $end
$upscope $end
$scope module cmdmem $end
$var wire 32 X cmd [31:0] $end
$var wire 32 Y addr [31:0] $end
$upscope $end
$scope module datamem $end
$var wire 32 Z addr [31:0] $end
$var wire 1 ! clk $end
$var wire 1 % writeMem $end
$var wire 32 [ writeData [31:0] $end
$var wire 32 \ data [31:0] $end
$upscope $end
$scope module pc $end
$var wire 1 ! clk $end
$var wire 32 ] nextaddr [31:0] $end
$var wire 1 " rst $end
$var reg 32 ^ addr [31:0] $end
$upscope $end
$scope module regfile $end
$var wire 1 ! clk $end
$var wire 5 _ ra1 [4:0] $end
$var wire 5 ` ra2 [4:0] $end
$var wire 32 a rd1 [31:0] $end
$var wire 32 b rd2 [31:0] $end
$var wire 1 " rst $end
$var wire 5 c wa [4:0] $end
$var wire 32 d wd [31:0] $end
$var wire 1 $ writeReg $end
$var integer 32 e i [31:0] $end
$upscope $end
$upscope $end
$upscope $end
$upscope $end
$enddefinitions $end
#0
$dumpvars
bx e
bx d
bx c
bx b
bx a
bx `
bx _
bx ^
bx ]
bx \
bx [
bx Z
bx Y
bx X
bx W
bx V
bx U
bx T
bx S
bx R
bx Q
bx P
bx O
bx N
bx M
bx L
bx K
bx J
bx I
bx H
bx G
bx F
bx E
bx D
bx C
bx B
bx A
bx @
bx ?
bx >
bx =
bx <
bx ;
bx :
bx 9
x8
x7
x6
x5
x4
x3
bx 2
bx 1
x0
x/
x.
x-
x,
x+
x*
x)
bx (
bx '
bx &
x%
x$
x#
1"
0!
$end
#1
b10001 ;
b10001 d
b0 K
b0 \
b10001 Q
b10001 Z
b100 F
b100 ]
1#
b10001 M
b10001 W
1$
b100 O
b10001 <
b10001 c
0*
1+
0/
b0 =
b10001 N
b10001 T
0.
0-
b0 '
b0 9
b0 :
b0 U
b1001010001000000000001000100 P
0)
04
b10001 (
b10001 2
b10001 J
b10001 H
b10001 I
b0 >
b0 A
b10001 B
b0 C
b0 [
b0 b
b10001 ?
b10001 `
b10010100010000000000010001 G
b0 D
b0 V
b0 a
b10010 @
b10010 _
00
0,
06
0%
03
05
07
08
b1000 &
b1000 1
b1000 E
b100010010100010000000000010001 L
b100010010100010000000000010001 X
b100 R
b0 S
b0 Y
b0 ^
b100000 e
1!
#2
0!
0"
#3
b10001 ;
b10001 d
b0 K
b0 \
0+
b10000 <
b10000 c
b10001 Q
b10001 Z
b0 N
b0 T
b1000110010100000000010000000 P
b10001 M
b10001 W
b1000 F
b1000 ]
b100000 (
b100000 2
b100000 J
b11111111111111111000000000100000 H
b1000000000100000 I
b10000 A
b10001100101000000000100000 G
b10010 B
b10010 ?
b10010 `
b10001 D
b10001 V
b10001 a
b10001 @
b10001 _
15
b0 &
b0 1
b0 E
b1000 O
b0 C
b0 [
b0 b
b10001100101000000000100000 L
b10001100101000000000100000 X
b1000 R
b100 S
b100 Y
b100 ^
1!
#4
0!
#5
b10001 ;
b10001 d
b10001 N
b10001 T
0$
1+
b0 <
b0 c
b10001 Q
b10001 Z
1.
b1000100 P
1#
b10001 M
b10001 W
b1000100 F
b1000100 ]
b10001 (
b10001 2
b10001 J
b10001 H
b10001 I
b0 A
b0 B
b0 ?
b0 `
b10001 G
b0 D
b0 V
b0 a
b0 @
b0 _
16
05
b10 &
b10 1
b10 E
b1100 O
b1000000000000000000000010001 L
b1000000000000000000000010001 X
b1100 R
b1000 S
b1000 Y
b1000 ^
1!
#6
0!
#7
b10110 ;
b10110 d
1$
b10001 <
b10001 c
b1001000 F
b1001000 ]
b10110 Q
b10110 Z
0.
b101 N
b101 T
b10001 =
b1000110001000000000000010100 P
b10110 M
b10110 W
b101 H
b101 I
b101 (
b101 2
b101 J
b10001 B
b10001 C
b10001 [
b10001 b
b10001 ?
b10001 `
b10001100010000000000000101 G
b10001 D
b10001 V
b10001 a
b10001 @
b10001 _
06
b1000 &
b1000 1
b1000 E
b1001000 O
b100010001100010000000000000101 L
b100010001100010000000000000101 X
b1001000 R
b1000100 S
b1000100 Y
b1000100 ^
1!
#8
0!
#9
b1001 N
b1001 T
b100100 P
b11111 <
b11111 c
b1001100 ;
b1001100 d
1.
b100100 F
b100100 ]
b1001 Q
b1001 Z
b1001 H
b1001 I
b1001 (
b1001 2
b1001 J
b0 B
b0 ?
b0 `
b1001 G
b0 @
b0 _
10
b11 &
b11 1
b11 E
b1001100 O
b1001 M
b1001 W
b0 =
b1100000000000000000000001001 L
b1100000000000000000000001001 X
b1001100 R
b1001000 S
b1001000 Y
b1001000 ^
b0 D
b0 V
b0 a
b0 C
b0 [
b0 b
1!
#10
0!
#11
b1011000 Q
b1011000 Z
0+
b10110 M
b10110 W
b101000 F
b101000 ]
1*
b10110 N
b10110 T
b10001100010001000000000 P
b1011000 =
b10001 <
b10001 c
0.
14
b0 (
b0 2
b0 J
b10 >
b11111111111111111000100010000000 H
b1000100010000000 I
b10001 A
b100011000100010000000 G
b10001 B
b10110 C
b10110 [
b10110 b
b10001 ?
b10001 `
00
15
b0 &
b0 1
b0 E
b101000 O
b1011000 ;
b1011000 d
b100011000100010000000 L
b100011000100010000000 X
b101000 R
b100100 S
b100100 Y
b100100 ^
1!
#12
0!
#13
1.
0$
b1001100 ;
b1001100 d
0*
b0 <
b0 c
1-
b1001100 P
b1001100 F
b1001100 ]
b0 K
b0 \
b1001100 Q
b1001100 Z
b1001100 M
b1001100 W
04
b1000 (
b1000 2
b1000 J
b0 >
b1000 H
b1000 I
b0 A
b0 B
b0 ?
b0 `
b11111000000000000000001000 G
b1001100 D
b1001100 V
b1001100 a
b11111 @
b11111 _
b101100 O
b0 =
b0 N
b0 T
b11111000000000000000001000 L
b11111000000000000000001000 X
b101100 R
b101000 S
b101000 Y
b101000 ^
b0 C
b0 [
b0 b
1!
#14
0!
#15
b0 ;
b0 d
0.
1$
1*
b1010000 F
b1010000 ]
b0 Q
b0 Z
0-
b0 P
0#
b0 M
b0 W
b0 H
b0 I
14
b0 (
b0 2
b0 J
b0 G
b0 D
b0 V
b0 a
b0 @
b0 _
b1010000 O
b0 L
b0 X
b1010000 R
b1001100 S
b1001100 Y
b1001100 ^
1!
#16
0!
#17
b1010100 F
b1010100 ]
b1010100 O
b1010100 R
b1010000 S
b1010000 Y
b1010000 ^
1!
#18
0!
#19
b1011000 F
b1011000 ]
b1011000 O
b1011000 R
b1010100 S
b1010100 Y
b1010100 ^
1!
#20
0!
#21
b1011100 F
b1011100 ]
b1011100 O
b1011100 R
b1011000 S
b1011000 Y
b1011000 ^
1!
#22
0!
#23
b1100000 F
b1100000 ]
b1100000 O
b1100000 R
b1011100 S
b1011100 Y
b1011100 ^
1!
#24
0!
#25
b1100100 F
b1100100 ]
b1100100 O
b1100100 R
b1100000 S
b1100000 Y
b1100000 ^
1!
#26
0!
#27
b10001 <
b10001 c
b0 ;
b0 d
0$
1+
b0 Q
b0 Z
0#
b0 M
b0 W
0*
b10001000000000000000000 P
b1011000 =
b0 N
b0 T
b1101000 F
b1101000 ]
b100010000000000000000 G
b10001 B
b1011000 C
b1011000 [
b1011000 b
b10001 ?
b10001 `
1%
13
05
b101011 &
b101011 1
b101011 E
b1101000 O
b10101100000100010000000000000000 L
b10101100000100010000000000000000 X
b1101000 R
b1100100 S
b1100100 Y
b1100100 ^
1!
#28
0!
#29
b1100 ;
b1100 d
b1100 Q
b1100 Z
1#
b1100 M
b1100 W
b10000 <
b10000 c
b1100 N
b1100 T
b10000000000000000110000 P
b10001 =
b1101100 F
b1101100 ]
b1100 H
b1100 I
04
b1100 (
b1100 2
b1100 J
b100000000000000001100 G
b10000 B
b10001 C
b10001 [
b10001 b
b10000 ?
b10000 `
b1101100 O
b10101100000100000000000000001100 L
b10101100000100000000000000001100 X
b1101100 R
b1101000 S
b1101000 Y
b1101000 ^
b0 K
b0 \
1!
#30
0!
#31
1$
b0 Q
b0 Z
0#
b0 M
b0 W
b1011000 ;
b1011000 d
b10000000000000000000000 P
b0 N
b0 T
b1110000 F
b1110000 ]
b100000000000000000000 G
b0 H
b0 I
14
b0 (
b0 2
b0 J
1,
0%
03
b100011 &
b100011 1
b100011 E
b1110000 O
b1011000 K
b1011000 \
b10001100000100000000000000000000 L
b10001100000100000000000000000000 X
b1110000 R
b1101100 S
b1101100 Y
b1101100 ^
1!
#32
0!
#33
0+
b0 <
b0 c
b0 ;
b0 d
1*
b0 P
b1110100 F
b1110100 ]
b0 G
b0 B
b0 ?
b0 `
0,
15
b0 &
b0 1
b0 E
b1110100 O
b0 =
b0 L
b0 X
b1110100 R
b1110000 S
b1110000 Y
b1110000 ^
b0 C
b0 [
b0 b
1!
#34
0!
#35
b1111000 F
b1111000 ]
b1111000 O
b1111000 R
b1110100 S
b1110100 Y
b1110100 ^
1!
#36
0!
#37
b1111100 F
b1111100 ]
b1111100 O
b1111100 R
b1111000 S
b1111000 Y
b1111000 ^
1!
#38
0!
#39
b10000000 F
b10000000 ]
b10000000 O
b10000000 R
b1111100 S
b1111100 Y
b1111100 ^
1!
