src/control_path.v
module control_path(
    input [5:0] opcode, funct,
    input zero,
    output JBEQ, JJRJAL, JAL, JR, RI, LW, SHIFT, SRL,
    output writeReg, writeMem,
    output reg [2:0] op
);

wire BEQ = opcode == 6'b000100;
wire BNE = opcode == 6'b000101;
wire RTYPE = opcode == 6'b000000;
wire SLL = funct == 6'b000000;
wire SW = opcode == 6'b101011;
wire J = opcode == 6'b000010;
// Это R тип?
assign RI = ~(RTYPE || BEQ || BNE);
// Сдвиг left/right? Сдвиг вообще?
assign SRL = funct == 6'b000010;
assign SHIFT = (RTYPE && SRL) || (RTYPE && SLL);
// Загрузка из памяти?
assign LW = opcode == 6'b100011;
// JAL / JR?
assign JR = RTYPE && funct == 6'b001000;
// BEQ/BNE прыжок
assign JBEQ = (BEQ && zero) || (BNE && ~zero);
// JAL?
assign JAL = (opcode == 6'b000011);
// Любой прямой прыжок
assign JJRJAL = J || JR || JAL;
// Запись в память и в регистровый файл (BEQ BNE SW J JR)
assign writeReg = ~(BEQ || BNE || SW || J || JR);
assign writeMem = SW;

// Выбор операции для ALU
always @(*) begin
    casex({opcode, funct})
    12'b000000_100000: op = 3'd0;
    12'b001000_xxxxxx: op = 3'd0;
    12'b000000_100010: op = 3'd1;
    12'b000100_xxxxxx: op = 3'd1;
    12'b000101_xxxxxx: op = 3'd1;
    12'b000000_100100: op = 3'd2;
    12'b001100_xxxxxx: op = 3'd2;
    12'b000000_100101: op = 3'd3;
    12'b001101_xxxxxx: op = 3'd3;
    12'b000000_100110: op = 3'd4;
    12'b001110_xxxxxx: op = 3'd4;
    default: op = 3'd0;
    endcase
end

endmodule

DATAMEM/datamem.v
// Little Endian
// Побайтная адресация
module datamem(
    input clk, writeMem,
    input [31:0] addr, writeData,
    output [31:0] data
);

reg [7:0] memory [0:32*4-1];

assign data = {memory[addr + 3], memory[addr + 2], memory[addr + 1], memory[addr]};

always @(posedge clk)
    if (writeMem) {memory[addr + 3], memory[addr + 2], memory[addr + 1], memory[addr]} <= writeData;

always @(posedge clk) $writememb("./_memory/data.mem", memory);

endmodule

src/ALU/alu.v
module alu(
    input [2:0] op,
    input [31:0] a, b,
    output reg [31:0] c,
    output zero
);

assign zero = |c;

always @(*) begin
    case (op)
        3'd0: c = a + b;
        3'd1: c = a - b;
        3'd2: c = a & b;
        3'd3: c = a | b;
        3'd4: c = a ^ b;
        default: c = a + b; 
    endcase
end

endmodule

REGFILE/regfile.v
// Регистры процессора (32)
// $0 — только для чтения (Константа 0)
module regfile(
    input clk, rst, writeReg,
    input [4:0] ra1, ra2, wa,
    input [31:0] wd,
    output [31:0] rd1, rd2
);

integer i;
reg [31:0] list [0:31];

assign rd1 = list[ra1];
assign rd2 = list[ra2];

always @(posedge clk) begin
    if (rst) for (i = 0; i < 32; i = i+1) begin 
        list[i] <= 32'd0;
    end
    else if (writeReg && wa != 32'd0) list[wa] <= wd;
end

endmodule

CMDMEM/cmdmem.v
// Little Endian
// Побайтная адресация
module cmdmem(
    input [31:0] addr,
    output [31:0] cmd
);

initial $readmemb("./_memory/cmd.mem", memory);

reg [7:0] memory [0:32*4-1];

assign cmd = {memory[addr + 3], memory[addr + 2], memory[addr + 1], memory[addr]};


endmodule

PC/pc.v
// Счетчик команд
module pc(
    input clk, rst,
    input [31:0] nextaddr,
    output reg [31:0] addr
);
    always @(posedge clk) begin
        if (rst) addr <= 32'd0;
        else addr <= nextaddr;
    end
endmodule

data_path.v
/*
JBEQ — Jump относительный (После beq/bne)
JJRJAL — Jump по прямому/псевдопрямому адресу
JAL — Выбор регистра $ra для записи при jal
JR – Выбор адреса для jump'а из регистра
RI – R или I инструкция
LW – Инструкция lw
SHIFT – Инструкиця сдвига
SRL – Выбор сдвига вправо (srl)
writeReg/writeMem – разрешение записи по clk в память
*/
module data_path(
    input clk, rst,
    input JBEQ, JJRJAL, JAL, JR, RI, LW, SHIFT, SRL,
    input writeReg, writeMem,
    input [2:0] op,
    output [5:0] opcode, funct,
    output zero
);

// PC + CMDMEM wires
wire [31:0] nextaddr, addr, cmd;
wire [31:0] addrDirect, addrRelate, addrAdd4;
// REGFILE wires
wire [4:0] wa;
wire [31:0] wd, rd1, rd2;
// ALU + near wires
wire [31:0] b, c;
wire [31:0] shiftRt;
// DATAMEM wires
wire [31:0] addrData, data;


// Выбор частей из шины команды
wire [4:0] rs, rt, rdR, shamt, rdI;
wire [15:0] immd;
wire [25:0] jaddr;
assign  opcode = cmd[31:26],
        rs = cmd[25:21],
        rt = cmd[20:16],
        rdR = cmd[15:11],
        shamt = cmd[10:6],
        funct = cmd[5:0],
        rdI = cmd[20:16],
        immd = cmd[15:0],
        jaddr = cmd[25:0];


// Расширение со знаком immd 16->32
wire [31:0] immd32;
assign immd32 = {{16{immd[15]}}, immd};
// Выбор нужного адреса записи для REGFILE
assign wa = JAL ? 5'd31 : (RI ? rdI : rdR);
// Выбор второго (b) значения ALU + сдвинутый rt 
assign b = RI ? immd32 : rd2;
assign shiftRt = SRL ? rd2 >> shamt : rd2 << shamt;
// Выбор адреса для Data Memory
assign addrData = SHIFT ? shiftRt : c;
// Выбор значения записи для REGFILE
assign wd = LW ? data : addrData;
// Выбор следующей команды для PC
assign addrAdd4 = addr + 4;
assign addrDirect = JR ? rd1 : {addr[31:28], jaddr, 2'b00};
assign addrRelate = JBEQ ? ((immd32 << 2) + addrAdd4) : addrAdd4;
assign nextaddr = JJRJAL ? addrDirect : addrRelate;


pc pc(.clk(clk), .rst(rst), .nextaddr(nextaddr), .addr(addr));
cmdmem cmdmem(.addr(addr), .cmd(cmd));
regfile regfile(.clk(clk), .rst(rst), .writeReg(writeReg),
                .ra1(rs), .ra2(rt), .wa(wa), .wd(wd),
                .rd1(rd1), .rd2(rd2));
alu alu(.op(op), .a(rd1), .b(b), .c(c), .zero(zero));
datamem datamem(.clk(clk), .writeMem(writeMem), .addr(addrData), .writeData(rd2), .data(data));


endmodule

cpu.v
module cpu(
    input clk, rst
);

wire JBEQ, JJRJAL, JAL, JR, RI, LW, SHIFT, SRL;
wire writeReg, writeMem;
wire [2:0] op;
wire [5:0] opcode, funct;
wire zero;

data_path data_path(.clk(clk), .rst(rst),
                    .JBEQ(JBEQ), .JJRJAL(JJRJAL), .JAL(JAL), .JR(JR), .RI(RI), .LW(LW), .SHIFT(SHIFT), .SRL(SRL),
                    .writeReg(writeReg), .writeMem(writeMem), .op(op),
                    .opcode(opcode), .funct(funct), .zero(zero));

control_path control_path(  .opcode(opcode), .funct(funct),
                            .zero(zero),
                            .JBEQ(JBEQ), .JJRJAL(JJRJAL), .JAL(JAL), .JR(JR), .RI(RI), .LW(LW), .SHIFT(SHIFT), .SRL(SRL),
                            .writeReg(writeReg), .writeMem(writeMem),
                            .op(op));

endmodule

test/test_cpu.v
module test_cpu();

reg clk, rst;
cpu testee(.clk(clk), .rst(rst));

initial begin
    $dumpfile("dump.vcd");
    $dumpvars(0, test_cpu);
end
initial #40 $finish;
initial #0 clk = 0;
initial #0 rst = 1;
initial #2 rst = 0;
always begin
    #1 clk = !clk;
end

endmodule

dump.vcd
$date
	Thu Feb 27 00:04:17 2020
$end
$version
	Icarus Verilog
$end
$timescale
	1s
$end
$scope module test_cpu $end
$var reg 1 ! clk $end
$var reg 1 " rst $end
$scope module testee $end
$var wire 1 ! clk $end
$var wire 1 " rst $end
$var wire 1 # zero $end
$var wire 1 $ writeReg $end
$var wire 1 % writeMem $end
$var wire 6 & opcode [5:0] $end
$var wire 3 ' op [2:0] $end
$var wire 6 ( funct [5:0] $end
$var wire 1 ) SRL $end
$var wire 1 * SHIFT $end
$var wire 1 + RI $end
$var wire 1 , LW $end
$var wire 1 - JR $end
$var wire 1 . JJRJAL $end
$var wire 1 / JBEQ $end
$var wire 1 0 JAL $end
$scope module control_path $end
$var wire 1 / JBEQ $end
$var wire 1 . JJRJAL $end
$var wire 1 - JR $end
$var wire 1 + RI $end
$var wire 1 * SHIFT $end
$var wire 1 % writeMem $end
$var wire 1 $ writeReg $end
$var wire 1 # zero $end
$var wire 6 1 opcode [5:0] $end
$var wire 6 2 funct [5:0] $end
$var wire 1 3 SW $end
$var wire 1 ) SRL $end
$var wire 1 4 SLL $end
$var wire 1 5 RTYPE $end
$var wire 1 , LW $end
$var wire 1 0 JAL $end
$var wire 1 6 J $end
$var wire 1 7 BNE $end
$var wire 1 8 BEQ $end
$var reg 3 9 op [2:0] $end
$upscope $end
$scope module data_path $end
$var wire 1 0 JAL $end
$var wire 1 / JBEQ $end
$var wire 1 . JJRJAL $end
$var wire 1 - JR $end
$var wire 1 , LW $end
$var wire 1 + RI $end
$var wire 1 * SHIFT $end
$var wire 1 ) SRL $end
$var wire 1 ! clk $end
$var wire 3 : op [2:0] $end
$var wire 1 " rst $end
$var wire 1 % writeMem $end
$var wire 1 $ writeReg $end
$var wire 1 # zero $end
$var wire 32 ; wd [31:0] $end
$var wire 5 < wa [4:0] $end
$var wire 32 = shiftRt [31:0] $end
$var wire 5 > shamt [4:0] $end
$var wire 5 ? rt [4:0] $end
$var wire 5 @ rs [4:0] $end
$var wire 5 A rdR [4:0] $end
$var wire 5 B rdI [4:0] $end
$var wire 32 C rd2 [31:0] $end
$var wire 32 D rd1 [31:0] $end
$var wire 6 E opcode [5:0] $end
$var wire 32 F nextaddr [31:0] $end
$var wire 26 G jaddr [25:0] $end
$var wire 32 H immd32 [31:0] $end
$var wire 16 I immd [15:0] $end
$var wire 6 J funct [5:0] $end
$var wire 32 K data [31:0] $end
$var wire 32 L cmd [31:0] $end
$var wire 32 M c [31:0] $end
$var wire 32 N b [31:0] $end
$var wire 32 O addrRelate [31:0] $end
$var wire 32 P addrDirect [31:0] $end
$var wire 32 Q addrData [31:0] $end
$var wire 32 R addrAdd4 [31:0] $end
$var wire 32 S addr [31:0] $end
$scope module alu $end
$var wire 32 T b [31:0] $end
$var wire 3 U op [2:0] $end
$var wire 1 # zero $end
$var wire 32 V a [31:0] $end
$var reg 32 W c [31:0] $end
$upscope $end
$scope module cmdmem $end
$var wire 32 X cmd [31:0] $end
$var wire 32 Y addr [31:0] $end
$upscope $end
$scope module datamem $end
$var wire 32 Z addr [31:0] $end
$var wire 1 ! clk $end
$var wire 1 % writeMem $end
$var wire 32 [ writeData [31:0] $end
$var wire 32 \ data [31:0] $end
$upscope $end
$scope module pc $end
$var wire 1 ! clk $end
$var wire 32 ] nextaddr [31:0] $end
$var wire 1 " rst $end
$var reg 32 ^ addr [31:0] $end
$upscope $end
$scope module regfile $end
$var wire 1 ! clk $end
$var wire 5 _ ra1 [4:0] $end
$var wire 5 ` ra2 [4:0] $end
$var wire 32 a rd1 [31:0] $end
$var wire 32 b rd2 [31:0] $end
$var wire 1 " rst $end
$var wire 5 c wa [4:0] $end
$var wire 32 d wd [31:0] $end
$var wire 1 $ writeReg $end
$var integer 32 e i [31:0] $end
$upscope $end
$upscope $end
$upscope $end
$upscope $end
$enddefinitions $end
#0
$dumpvars
bx e
bx d
bx c
bx b
bx a
bx `
bx _
bx ^
bx ]
bx \
bx [
bx Z
bx Y
bx X
bx W
bx V
bx U
bx T
bx S
bx R
bx Q
bx P
bx O
bx N
bx M
bx L
bx K
bx J
bx I
bx H
bx G
bx F
bx E
bx D
bx C
bx B
bx A
bx @
bx ?
bx >
bx =
bx <
bx ;
bx :
bx 9
x8
x7
x6
x5
x4
x3
bx 2
bx 1
x0
x/
x.
x-
x,
x+
x*
x)
bx (
bx '
bx &
x%
x$
x#
1"
0!
$end
#1
b0 ;
b0 d
b0 K
b0 \
b0 Q
b0 Z
b100 F
b100 ]
0#
b0 M
b0 W
1$
b100 O
b10000 <
b10000 c
0*
0+
0/
b0 =
b0 N
b0 T
0.
0-
b0 '
b0 9
b0 :
b0 U
b100001001100000000010000000 P
0)
04
b100000 (
b100000 2
b100000 J
b11111111111111111000000000100000 H
b1000000000100000 I
b0 >
b10000 A
b1001 B
b0 C
b0 [
b0 b
b1001 ?
b1001 `
b1000010011000000000100000 G
b0 D
b0 V
b0 a
b1000 @
b1000 _
00
0,
06
0%
03
15
07
08
b0 &
b0 1
b0 E
b1000010011000000000100000 L
b1000010011000000000100000 X
b100 R
b0 S
b0 Y
b0 ^
b100000 e
1!
#2
0!
0"
#3
1*
b0 <
b0 c
b0 P
b1000 F
b1000 ]
14
b0 (
b0 2
b0 J
b0 H
b0 I
b0 A
b0 B
b0 ?
b0 `
b0 G
b0 @
b0 _
b1000 O
b0 L
b0 X
b1000 R
b100 S
b100 Y
b100 ^
1!
#4
0!
#5
0*
b10000 <
b10000 c
b10 '
b10 9
b10 :
b10 U
b1000010010100000000010010000 P
b1100 F
b1100 ]
04
b100100 (
b100100 2
b100100 J
b11111111111111111000000000100100 H
b1000000000100100 I
b10000 A
b10010 B
b10010 ?
b10010 `
b10000100101000000000100100 G
b10000 @
b10000 _
b1100 O
b10000100101000000000100100 L
b10000100101000000000100100 X
b1100 R
b1000 S
b1000 Y
b1000 ^
1!
#6
0!
#7
1*
b0 <
b0 c
b0 '
b0 9
b0 :
b0 U
b0 P
b10000 F
b10000 ]
14
b0 (
b0 2
b0 J
b0 H
b0 I
b0 A
b0 B
b0 ?
b0 `
b0 G
b0 @
b0 _
b10000 O
b0 L
b0 X
b10000 R
b1100 S
b1100 Y
b1100 ^
1!
#8
0!
#9
b1000 <
b1000 c
b10000010000001000000000 P
b10100 F
b10100 ]
b10 >
b100000010000000 H
b100000010000000 I
b1000 A
b100000100000010000000 G
b10000 B
b10000 ?
b10000 `
b10100 O
b100000100000010000000 L
b100000100000010000000 X
b10100 R
b10000 S
b10000 Y
b10000 ^
1!
#10
0!
#11
b0 <
b0 c
b0 P
b11000 F
b11000 ]
b0 >
b0 H
b0 I
b0 A
b0 G
b0 B
b0 ?
b0 `
b11000 O
b0 L
b0 X
b11000 R
b10100 S
b10100 Y
b10100 ^
1!
#12
0!
#13
b100011 ;
b100011 d
b100011 Q
b100011 Z
b10000 <
b10000 c
1#
b100011 M
b100011 W
b100011 N
b100011 T
1+
0*
b100110000000000000010001100 P
b11100 F
b11100 ]
b100011 H
b100011 I
04
b100011 (
b100011 2
b100011 J
b10000 B
b10000 ?
b10000 `
b1001100000000000000100011 G
b1001 @
b1001 _
05
b1000 &
b1000 1
b1000 E
b11100 O
b100001001100000000000000100011 L
b100001001100000000000000100011 X
b11100 R
b11000 S
b11000 Y
b11000 ^
1!
#14
0!
#15
b0 ;
b0 d
0#
b0 Q
b0 Z
1.
0$
0+
b0 M
b0 W
b0 <
b0 c
b0 N
b0 T
b0 P
1-
b0 F
b0 ]
b1000 H
b1000 I
b1000 (
b1000 2
b1000 J
b0 B
b0 ?
b0 `
b10001000000000000000001000 G
b10001 @
b10001 _
15
b0 &
b0 1
b0 E
b100000 O
b0 C
b0 [
b0 b
b10001000000000000000001000 L
b10001000000000000000001000 X
b100000 R
b11100 S
b11100 Y
b11100 ^
1!
#16
0!
#17
0.
1$
b100 F
b100 ]
b100001001100000000010000000 P
b10000 <
b10000 c
0-
b100000 (
b100000 2
b100000 J
b11111111111111111000000000100000 H
b1000000000100000 I
b10000 A
b1001 B
b1001 ?
b1001 `
b1000010011000000000100000 G
b1000 @
b1000 _
b100 O
b1000010011000000000100000 L
b1000010011000000000100000 X
b100 R
b0 S
b0 Y
b0 ^
1!
#18
0!
#19
1*
b0 <
b0 c
b0 P
b1000 F
b1000 ]
14
b0 (
b0 2
b0 J
b0 H
b0 I
b0 A
b0 B
b0 ?
b0 `
b0 G
b0 @
b0 _
b1000 O
b0 L
b0 X
b1000 R
b100 S
b100 Y
b100 ^
1!
#20
0!
#21
0*
b10000 <
b10000 c
b10 '
b10 9
b10 :
b10 U
b1000010010100000000010010000 P
b1100 F
b1100 ]
04
b100100 (
b100100 2
b100100 J
b11111111111111111000000000100100 H
b1000000000100100 I
b10000 A
b10010 B
b10010 ?
b10010 `
b10000100101000000000100100 G
b10000 @
b10000 _
b1100 O
b10000100101000000000100100 L
b10000100101000000000100100 X
b1100 R
b1000 S
b1000 Y
b1000 ^
1!
#22
0!
#23
1*
b0 <
b0 c
b0 '
b0 9
b0 :
b0 U
b0 P
b10000 F
b10000 ]
14
b0 (
b0 2
b0 J
b0 H
b0 I
b0 A
b0 B
b0 ?
b0 `
b0 G
b0 @
b0 _
b10000 O
b0 L
b0 X
b10000 R
b1100 S
b1100 Y
b1100 ^
1!
#24
0!
#25
b1000 <
b1000 c
b10000010000001000000000 P
b10100 F
b10100 ]
b10 >
b100000010000000 H
b100000010000000 I
b1000 A
b100000100000010000000 G
b10000 B
b10000 ?
b10000 `
b10100 O
b100000100000010000000 L
b100000100000010000000 X
b10100 R
b10000 S
b10000 Y
b10000 ^
1!
#26
0!
#27
b0 <
b0 c
b0 P
b11000 F
b11000 ]
b0 >
b0 H
b0 I
b0 A
b0 G
b0 B
b0 ?
b0 `
b11000 O
b0 L
b0 X
b11000 R
b10100 S
b10100 Y
b10100 ^
1!
#28
0!
#29
b100011 ;
b100011 d
b100011 Q
b100011 Z
b10000 <
b10000 c
1#
b100011 M
b100011 W
b100011 N
b100011 T
1+
0*
b100110000000000000010001100 P
b11100 F
b11100 ]
b100011 H
b100011 I
04
b100011 (
b100011 2
b100011 J
b10000 B
b10000 ?
b10000 `
b1001100000000000000100011 G
b1001 @
b1001 _
05
b1000 &
b1000 1
b1000 E
b11100 O
b100001001100000000000000100011 L
b100001001100000000000000100011 X
b11100 R
b11000 S
b11000 Y
b11000 ^
1!
#30
0!
#31
b0 ;
b0 d
0#
b0 Q
b0 Z
1.
0$
0+
b0 M
b0 W
b0 <
b0 c
b0 N
b0 T
b0 P
1-
b0 F
b0 ]
b1000 H
b1000 I
b1000 (
b1000 2
b1000 J
b0 B
b0 ?
b0 `
b10001000000000000000001000 G
b10001 @
b10001 _
15
b0 &
b0 1
b0 E
b100000 O
b0 C
b0 [
b0 b
b10001000000000000000001000 L
b10001000000000000000001000 X
b100000 R
b11100 S
b11100 Y
b11100 ^
1!
#32
0!
#33
0.
1$
b100 F
b100 ]
b100001001100000000010000000 P
b10000 <
b10000 c
0-
b100000 (
b100000 2
b100000 J
b11111111111111111000000000100000 H
b1000000000100000 I
b10000 A
b1001 B
b1001 ?
b1001 `
b1000010011000000000100000 G
b1000 @
b1000 _
b100 O
b1000010011000000000100000 L
b1000010011000000000100000 X
b100 R
b0 S
b0 Y
b0 ^
1!
#34
0!
#35
1*
b0 <
b0 c
b0 P
b1000 F
b1000 ]
14
b0 (
b0 2
b0 J
b0 H
b0 I
b0 A
b0 B
b0 ?
b0 `
b0 G
b0 @
b0 _
b1000 O
b0 L
b0 X
b1000 R
b100 S
b100 Y
b100 ^
1!
#36
0!
#37
0*
b10000 <
b10000 c
b10 '
b10 9
b10 :
b10 U
b1000010010100000000010010000 P
b1100 F
b1100 ]
04
b100100 (
b100100 2
b100100 J
b11111111111111111000000000100100 H
b1000000000100100 I
b10000 A
b10010 B
b10010 ?
b10010 `
b10000100101000000000100100 G
b10000 @
b10000 _
b1100 O
b10000100101000000000100100 L
b10000100101000000000100100 X
b1100 R
b1000 S
b1000 Y
b1000 ^
1!
#38
0!
#39
1*
b0 <
b0 c
b0 '
b0 9
b0 :
b0 U
b0 P
b10000 F
b10000 ]
14
b0 (
b0 2
b0 J
b0 H
b0 I
b0 A
b0 B
b0 ?
b0 `
b0 G
b0 @
b0 _
b10000 O
b0 L
b0 X
b10000 R
b1100 S
b1100 Y
b1100 ^
1!
