src/control_path.v
module control_path(
    input [5:0] opcode, funct,
    input zero,
    output JBEQ, JJRJAL, JAL, JR, RI, LW, SHIFT, SRL,
    output writeReg, writeMem,
    output reg [2:0] op
);

wire BEQ = opcode == 6'b000100;
wire BNE = opcode == 6'b000101;
wire RTYPE = opcode == 6'b000000;
wire SLL = funct == 6'b000000;
wire SW = opcode == 6'b101011;
wire J = opcode == 6'b000010;
// Это R тип?
assign RI = ~(RTYPE || BEQ || BNE);
// Сдвиг left/right? Сдвиг вообще?
assign SRL = funct == 6'b000010;
assign SHIFT = (RTYPE && SRL) || (RTYPE && SLL);
// Загрузка из памяти?
assign LW = opcode == 6'b100011;
// JAL / JR?
assign JR = RTYPE && funct == 6'b001000;
// BEQ/BNE прыжок
assign JBEQ = (BEQ && zero) || (BNE && ~zero);
// JAL?
assign JAL = (opcode == 6'b000011);
// Любой прямой прыжок
assign JJRJAL = J || JR || JAL;
// Запись в память и в регистровый файл (BEQ BNE SW J JR)
assign writeReg = ~(BEQ || BNE || SW || J || JR);
assign writeMem = SW;

// Выбор операции для ALU
always @(*) begin
    casex({opcode, funct})
    12'b000000_100000: op = 3'd0;
    12'b001000_xxxxxx: op = 3'd0;
    12'b000000_100010: op = 3'd1;
    12'b000100_xxxxxx: op = 3'd1;
    12'b000101_xxxxxx: op = 3'd1;
    12'b000000_100100: op = 3'd2;
    12'b001100_xxxxxx: op = 3'd2;
    12'b000000_100101: op = 3'd3;
    12'b001101_xxxxxx: op = 3'd3;
    12'b000000_100110: op = 3'd4;
    12'b001110_xxxxxx: op = 3'd4;
    default: op = 3'd0;
    endcase
end

endmodule

DATAMEM/datamem.v
// Little Endian
// Побайтная адресация
module datamem(
    input clk, writeMem,
    input [31:0] addr, writeData,
    output [31:0] data
);

reg [7:0] memory [0:32*4-1];

assign data = {memory[addr + 3], memory[addr + 2], memory[addr + 1], memory[addr]};

always @(posedge clk)
    if (writeMem) {memory[addr + 3], memory[addr + 2], memory[addr + 1], memory[addr]} <= writeData;

always @(posedge clk) $writememb("./_memory/data.mem", memory);

endmodule

src/ALU/alu.v
module alu(
    input [2:0] op,
    input [31:0] a, b,
    output reg [31:0] c,
    output zero
);

assign zero = ~(|c);

always @(*) begin
    case (op)
        3'd0: c = a + b;
        3'd1: c = a - b;
        3'd2: c = a & b;
        3'd3: c = a | b;
        3'd4: c = a ^ b;
        default: c = a + b; 
    endcase
end

endmodule

REGFILE/regfile.v
// Регистры процессора (32)
// $0 — только для чтения (Константа 0)
module regfile(
    input clk, rst, writeReg,
    input [4:0] ra1, ra2, wa,
    input [31:0] wd,
    output [31:0] rd1, rd2
);

integer i;
reg [31:0] list [0:31];

assign rd1 = list[ra1];
assign rd2 = list[ra2];

always @(posedge clk) begin
    if (rst) for (i = 0; i < 32; i = i+1) begin 
        list[i] <= 32'd0;
    end
    else if (writeReg && wa != 32'd0) list[wa] <= wd;
end

endmodule

CMDMEM/cmdmem.v
// Little Endian
// Побайтная адресация
module cmdmem(
    input [31:0] addr,
    output [31:0] cmd
);

initial $readmemb("./_memory/cmd.mem", memory);

reg [7:0] memory [0:32*4-1];

assign cmd = {memory[addr + 3], memory[addr + 2], memory[addr + 1], memory[addr]};


endmodule

PC/pc.v
// Счетчик команд
module pc(
    input clk, rst,
    input [31:0] nextaddr,
    output reg [31:0] addr
);
    always @(posedge clk) begin
        if (rst) addr <= 32'd0;
        else addr <= nextaddr;
    end
endmodule

data_path.v
/*
JBEQ — Jump относительный (После beq/bne)
JJRJAL — Jump по прямому/псевдопрямому адресу
JAL — Выбор регистра $ra для записи при jal
JR – Выбор адреса для jump'а из регистра
RI – R или I инструкция
LW – Инструкция lw
SHIFT – Инструкиця сдвига
SRL – Выбор сдвига вправо (srl)
writeReg/writeMem – разрешение записи по clk в память
*/
module data_path(
    input clk, rst,
    input JBEQ, JJRJAL, JAL, JR, RI, LW, SHIFT, SRL,
    input writeReg, writeMem,
    input [2:0] op,
    output [5:0] opcode, funct,
    output zero
);

// PC + CMDMEM wires
wire [31:0] nextaddr, addr, cmd;
wire [31:0] addrDirect, addrRelate, addrAdd4;
// REGFILE wires
wire [4:0] wa;
wire [31:0] wd, rd1, rd2;
// ALU + near wires
wire [31:0] b, c;
wire [31:0] shiftRt;
// DATAMEM wires
wire [31:0] addrData, data;


// Выбор частей из шины команды
wire [4:0] rs, rt, rdR, shamt, rdI;
wire [15:0] immd;
wire [25:0] jaddr;
assign  opcode = cmd[31:26],
        rs = cmd[25:21],
        rt = cmd[20:16],
        rdR = cmd[15:11],
        shamt = cmd[10:6],
        funct = cmd[5:0],
        rdI = cmd[20:16],
        immd = cmd[15:0],
        jaddr = cmd[25:0];


// Расширение со знаком immd 16->32
wire [31:0] immd32;
assign immd32 = {{16{immd[15]}}, immd};
// Выбор нужного адреса записи для REGFILE
assign wa = JAL ? 5'd31 : (RI ? rdI : rdR);
// Выбор второго (b) значения ALU + сдвинутый rt 
assign b = RI ? immd32 : rd2;
assign shiftRt = SRL ? rd2 >> shamt : rd2 << shamt;
// Выбор адреса для Data Memory
assign addrData = SHIFT ? shiftRt : c;
// Выбор значения записи для REGFILE
assign wd = LW ? data : addrData;
// Выбор следующей команды для PC
assign addrAdd4 = addr + 4;
assign addrDirect = JR ? rd1 : {addr[31:28], jaddr, 2'b00};
assign addrRelate = JBEQ ? ((immd32 << 2) + addrAdd4) : addrAdd4;
assign nextaddr = JJRJAL ? addrDirect : addrRelate;


pc pc(.clk(clk), .rst(rst), .nextaddr(nextaddr), .addr(addr));
cmdmem cmdmem(.addr(addr), .cmd(cmd));
regfile regfile(.clk(clk), .rst(rst), .writeReg(writeReg),
                .ra1(rs), .ra2(rt), .wa(wa), .wd(wd),
                .rd1(rd1), .rd2(rd2));
alu alu(.op(op), .a(rd1), .b(b), .c(c), .zero(zero));
datamem datamem(.clk(clk), .writeMem(writeMem), .addr(addrData), .writeData(rd2), .data(data));


endmodule

cpu.v
module cpu(
    input clk, rst
);

wire JBEQ, JJRJAL, JAL, JR, RI, LW, SHIFT, SRL;
wire writeReg, writeMem;
wire [2:0] op;
wire [5:0] opcode, funct;
wire zero;

data_path data_path(.clk(clk), .rst(rst),
                    .JBEQ(JBEQ), .JJRJAL(JJRJAL), .JAL(JAL), .JR(JR), .RI(RI), .LW(LW), .SHIFT(SHIFT), .SRL(SRL),
                    .writeReg(writeReg), .writeMem(writeMem), .op(op),
                    .opcode(opcode), .funct(funct), .zero(zero));

control_path control_path(  .opcode(opcode), .funct(funct),
                            .zero(zero),
                            .JBEQ(JBEQ), .JJRJAL(JJRJAL), .JAL(JAL), .JR(JR), .RI(RI), .LW(LW), .SHIFT(SHIFT), .SRL(SRL),
                            .writeReg(writeReg), .writeMem(writeMem),
                            .op(op));

endmodule

test/test_cpu.v
module test_cpu();

reg clk, rst;
cpu testee(.clk(clk), .rst(rst));

initial begin
    $dumpfile("dump.vcd");
    $dumpvars(0, test_cpu);
end
initial #66 $finish;
initial #0 clk = 0;
initial #0 rst = 1;
initial #2 rst = 0;
always begin
    #1 clk = !clk;
end

endmodule

dump.vcd
$date
	Thu Feb 27 15:22:17 2020
$end
$version
	Icarus Verilog
$end
$timescale
	1s
$end
$scope module test_cpu $end
$var reg 1 ! clk $end
$var reg 1 " rst $end
$scope module testee $end
$var wire 1 ! clk $end
$var wire 1 " rst $end
$var wire 1 # zero $end
$var wire 1 $ writeReg $end
$var wire 1 % writeMem $end
$var wire 6 & opcode [5:0] $end
$var wire 3 ' op [2:0] $end
$var wire 6 ( funct [5:0] $end
$var wire 1 ) SRL $end
$var wire 1 * SHIFT $end
$var wire 1 + RI $end
$var wire 1 , LW $end
$var wire 1 - JR $end
$var wire 1 . JJRJAL $end
$var wire 1 / JBEQ $end
$var wire 1 0 JAL $end
$scope module control_path $end
$var wire 1 / JBEQ $end
$var wire 1 . JJRJAL $end
$var wire 1 - JR $end
$var wire 1 + RI $end
$var wire 1 * SHIFT $end
$var wire 1 % writeMem $end
$var wire 1 $ writeReg $end
$var wire 1 # zero $end
$var wire 6 1 opcode [5:0] $end
$var wire 6 2 funct [5:0] $end
$var wire 1 3 SW $end
$var wire 1 ) SRL $end
$var wire 1 4 SLL $end
$var wire 1 5 RTYPE $end
$var wire 1 , LW $end
$var wire 1 0 JAL $end
$var wire 1 6 J $end
$var wire 1 7 BNE $end
$var wire 1 8 BEQ $end
$var reg 3 9 op [2:0] $end
$upscope $end
$scope module data_path $end
$var wire 1 0 JAL $end
$var wire 1 / JBEQ $end
$var wire 1 . JJRJAL $end
$var wire 1 - JR $end
$var wire 1 , LW $end
$var wire 1 + RI $end
$var wire 1 * SHIFT $end
$var wire 1 ) SRL $end
$var wire 1 ! clk $end
$var wire 3 : op [2:0] $end
$var wire 1 " rst $end
$var wire 1 % writeMem $end
$var wire 1 $ writeReg $end
$var wire 1 # zero $end
$var wire 32 ; wd [31:0] $end
$var wire 5 < wa [4:0] $end
$var wire 32 = shiftRt [31:0] $end
$var wire 5 > shamt [4:0] $end
$var wire 5 ? rt [4:0] $end
$var wire 5 @ rs [4:0] $end
$var wire 5 A rdR [4:0] $end
$var wire 5 B rdI [4:0] $end
$var wire 32 C rd2 [31:0] $end
$var wire 32 D rd1 [31:0] $end
$var wire 6 E opcode [5:0] $end
$var wire 32 F nextaddr [31:0] $end
$var wire 26 G jaddr [25:0] $end
$var wire 32 H immd32 [31:0] $end
$var wire 16 I immd [15:0] $end
$var wire 6 J funct [5:0] $end
$var wire 32 K data [31:0] $end
$var wire 32 L cmd [31:0] $end
$var wire 32 M c [31:0] $end
$var wire 32 N b [31:0] $end
$var wire 32 O addrRelate [31:0] $end
$var wire 32 P addrDirect [31:0] $end
$var wire 32 Q addrData [31:0] $end
$var wire 32 R addrAdd4 [31:0] $end
$var wire 32 S addr [31:0] $end
$scope module alu $end
$var wire 32 T b [31:0] $end
$var wire 3 U op [2:0] $end
$var wire 1 # zero $end
$var wire 32 V a [31:0] $end
$var reg 32 W c [31:0] $end
$upscope $end
$scope module cmdmem $end
$var wire 32 X cmd [31:0] $end
$var wire 32 Y addr [31:0] $end
$upscope $end
$scope module datamem $end
$var wire 32 Z addr [31:0] $end
$var wire 1 ! clk $end
$var wire 1 % writeMem $end
$var wire 32 [ writeData [31:0] $end
$var wire 32 \ data [31:0] $end
$upscope $end
$scope module pc $end
$var wire 1 ! clk $end
$var wire 32 ] nextaddr [31:0] $end
$var wire 1 " rst $end
$var reg 32 ^ addr [31:0] $end
$upscope $end
$scope module regfile $end
$var wire 1 ! clk $end
$var wire 5 _ ra1 [4:0] $end
$var wire 5 ` ra2 [4:0] $end
$var wire 32 a rd1 [31:0] $end
$var wire 32 b rd2 [31:0] $end
$var wire 1 " rst $end
$var wire 5 c wa [4:0] $end
$var wire 32 d wd [31:0] $end
$var wire 1 $ writeReg $end
$var integer 32 e i [31:0] $end
$upscope $end
$upscope $end
$upscope $end
$upscope $end
$enddefinitions $end
#0
$dumpvars
bx e
bx d
bx c
bx b
bx a
bx `
bx _
bx ^
bx ]
bx \
bx [
bx Z
bx Y
bx X
bx W
bx V
bx U
bx T
bx S
bx R
bx Q
bx P
bx O
bx N
bx M
bx L
bx K
bx J
bx I
bx H
bx G
bx F
bx E
bx D
bx C
bx B
bx A
bx @
bx ?
bx >
bx =
bx <
bx ;
bx :
bx 9
x8
x7
x6
x5
x4
x3
bx 2
bx 1
x0
x/
x.
x-
x,
x+
x*
x)
bx (
bx '
bx &
x%
x$
x#
1"
0!
$end
#1
b1100 ;
b1100 d
0#
b0 K
b0 \
b1100 Q
b1100 Z
b100 F
b100 ]
b1100 M
b1100 W
1$
b100 O
b1000 <
b1000 c
0*
1+
0/
b0 =
b1100 N
b1100 T
0.
0-
b0 '
b0 9
b0 :
b0 U
b1000000000000000110000 P
0)
04
b1100 (
b1100 2
b1100 J
b1100 H
b1100 I
b0 >
b0 A
b1000 B
b0 C
b0 [
b0 b
b1000 ?
b1000 `
b10000000000000001100 G
b0 D
b0 V
b0 a
b0 @
b0 _
00
0,
06
0%
03
05
07
08
b1000 &
b1000 1
b1000 E
b100000000010000000000000001100 L
b100000000010000000000000001100 X
b100 R
b0 S
b0 Y
b0 ^
b100000 e
1!
#2
0!
0"
#3
b11000 ;
b11000 d
b11000 Q
b11000 Z
b11000 M
b11000 W
b1001 <
b1001 c
b11000 N
b11000 T
b1001000000000001100000 P
b1000 F
b1000 ]
b11000 H
b11000 I
b11000 (
b11000 2
b11000 J
b10010000000000011000 G
b1001 B
b1001 ?
b1001 `
b1000 O
b0 C
b0 [
b0 b
b100000000010010000000000011000 L
b100000000010010000000000011000 X
b1000 R
b100 S
b100 Y
b100 ^
1!
#4
0!
#5
b0 ;
b0 d
1#
b0 Q
b0 Z
0+
b0 M
b0 W
b0 <
b0 c
1*
b0 N
b0 T
b0 P
b1100 F
b1100 ]
b0 H
b0 I
14
b0 (
b0 2
b0 J
b0 G
b0 B
b0 ?
b0 `
15
b0 &
b0 1
b0 E
b1100 O
b0 =
b0 L
b0 X
b1100 R
b1000 S
b1000 Y
b1000 ^
b0 C
b0 [
b0 b
1!
#6
0!
#7
b100100 ;
b100100 d
0*
b10000 <
b10000 c
b100100 Q
b100100 Z
0#
b1100 =
b1100 N
b1100 T
b100101000100000000010000000 P
b100100 M
b100100 W
b10000 F
b10000 ]
04
b100000 (
b100000 2
b100000 J
b11111111111111111000000000100000 H
b1000000000100000 I
b10000 A
b1000 B
b1100 C
b1100 [
b1100 b
b1000 ?
b1000 `
b1001010001000000000100000 G
b11000 D
b11000 V
b11000 a
b1001 @
b1001 _
b10000 O
b1001010001000000000100000 L
b1001010001000000000100000 X
b10000 R
b1100 S
b1100 Y
b1100 ^
1!
#8
0!
#9
b1100 ;
b1100 d
b1100 Q
b1100 Z
b1100 M
b1100 W
b10001 <
b10001 c
b1 '
b1 9
b1 :
b1 U
b100101000100010000010001000 P
b10100 F
b10100 ]
b100010 (
b100010 2
b100010 J
b1001010001000100000100010 G
b11111111111111111000100000100010 H
b1000100000100010 I
b10001 A
b10100 O
b1001010001000100000100010 L
b1001010001000100000100010 X
b10100 R
b10000 S
b10000 Y
b10000 ^
1!
#10
0!
#11
b1000 ;
b1000 d
b1000 Q
b1000 Z
b1000 M
b1000 W
b10010 <
b10010 c
b10 '
b10 9
b10 :
b10 U
b100101000100100000010010000 P
b11000 F
b11000 ]
b100100 (
b100100 2
b100100 J
b1001010001001000000100100 G
b11111111111111111001000000100100 H
b1001000000100100 I
b10010 A
b11000 O
b1001010001001000000100100 L
b1001010001001000000100100 X
b11000 R
b10100 S
b10100 Y
b10100 ^
1!
#12
0!
#13
b11100 ;
b11100 d
b11100 Q
b11100 Z
b11100 M
b11100 W
b10011 <
b10011 c
b11 '
b11 9
b11 :
b11 U
b100101000100110000010010100 P
b11100 F
b11100 ]
b100101 (
b100101 2
b100101 J
b1001010001001100000100101 G
b11111111111111111001100000100101 H
b1001100000100101 I
b10011 A
b11100 O
b1001010001001100000100101 L
b1001010001001100000100101 X
b11100 R
b11000 S
b11000 Y
b11000 ^
1!
#14
0!
#15
b10100 ;
b10100 d
b10100 Q
b10100 Z
b10100 M
b10100 W
b10100 <
b10100 c
b100 '
b100 9
b100 :
b100 U
b100101000101000000010011000 P
b100000 F
b100000 ]
b100110 (
b100110 2
b100110 J
b1001010001010000000100110 G
b11111111111111111010000000100110 H
b1010000000100110 I
b10100 A
b100000 O
b1001010001010000000100110 L
b1001010001010000000100110 X
b100000 R
b11100 S
b11100 Y
b11100 ^
1!
#16
0!
#17
b1100000 ;
b1100000 d
1*
b10101 <
b10101 c
b1100000 Q
b1100000 Z
b0 '
b0 9
b0 :
b0 U
b1100000 =
b11000 N
b11000 T
b1001101010001000000000 P
b11000 M
b11000 W
b100100 F
b100100 ]
14
b0 (
b0 2
b0 J
b10 >
b11111111111111111010100010000000 H
b1010100010000000 I
b10101 A
b1001 B
b11000 C
b11000 [
b11000 b
b1001 ?
b1001 `
b10011010100010000000 G
b0 D
b0 V
b0 a
b0 @
b0 _
b100100 O
b10011010100010000000 L
b10011010100010000000 X
b100100 R
b100000 S
b100000 Y
b100000 ^
1!
#18
0!
#19
b110 ;
b110 d
b110 Q
b110 Z
b10110 <
b10110 c
b110 =
b1001101100001000001000 P
b101000 F
b101000 ]
1)
04
b10 (
b10 2
b10 J
b10011011000010000010 G
b11111111111111111011000010000010 H
b1011000010000010 I
b10110 A
b101000 O
b10011011000010000010 L
b10011011000010000010 X
b101000 R
b100100 S
b100100 Y
b100100 ^
1!
#20
0!
#21
b0 ;
b0 d
1#
b0 <
b0 c
b0 Q
b0 Z
b0 M
b0 W
b0 P
b0 =
b0 N
b0 T
b101100 F
b101100 ]
0)
14
b0 (
b0 2
b0 J
b0 >
b0 H
b0 I
b0 A
b0 G
b0 B
b0 C
b0 [
b0 b
b0 ?
b0 `
b101100 O
b0 L
b0 X
b101100 R
b101000 S
b101000 Y
b101000 ^
1!
#22
0!
#23
b1101 ;
b1101 d
b1011 <
b1011 c
b1 N
b1 T
b1101 Q
b1101 Z
1+
0#
0*
b100001011000000000000000100 P
b1101 M
b1101 W
b110000 F
b110000 ]
b1 H
b1 I
04
b1 (
b1 2
b1 J
b1011 B
b1011 ?
b1011 `
b1000010110000000000000001 G
b1100 D
b1100 V
b1100 a
b1000 @
b1000 _
05
b1000 &
b1000 1
b1000 E
b110000 O
b100001000010110000000000000001 L
b100001000010110000000000000001 X
b110000 R
b101100 S
b101100 Y
b101100 ^
1!
#24
0!
#25
b100 ;
b100 d
b100 Q
b100 Z
b1100 <
b1100 c
b100 M
b100 W
b110 N
b110 T
b100001100000000000000011000 P
b10 '
b10 9
b10 :
b10 U
b110100 F
b110100 ]
b110 H
b110 I
b110 (
b110 2
b110 J
b1000011000000000000000110 G
b1100 B
b1100 ?
b1100 `
b1100 &
b1100 1
b1100 E
b110100 O
b0 =
b110001000011000000000000000110 L
b110001000011000000000000000110 X
b110100 R
b110000 S
b110000 Y
b110000 ^
b0 C
b0 [
b0 b
1!
#26
0!
#27
b1110 ;
b1110 d
b1110 Q
b1110 Z
b1101 <
b1101 c
b1110 M
b1110 W
b100001101000000000000011000 P
b11 '
b11 9
b11 :
b11 U
b111000 F
b111000 ]
b1000011010000000000000110 G
b1101 B
b1101 ?
b1101 `
b1101 &
b1101 1
b1101 E
b111000 O
b0 C
b0 [
b0 b
b110101000011010000000000000110 L
b110101000011010000000000000110 X
b111000 R
b110100 S
b110100 Y
b110100 ^
1!
#28
0!
#29
b1010 ;
b1010 d
b1010 Q
b1010 Z
b1110 <
b1110 c
b1010 M
b1010 W
b100001110000000000000011000 P
b100 '
b100 9
b100 :
b100 U
b111100 F
b111100 ]
b1000011100000000000000110 G
b1110 B
b1110 ?
b1110 `
b1110 &
b1110 1
b1110 E
b111100 O
b0 =
b111001000011100000000000000110 L
b111001000011100000000000000110 X
b111100 R
b111000 S
b111000 Y
b111000 ^
b0 C
b0 [
b0 b
1!
#30
0!
#31
b0 ;
b0 d
1#
0+
b0 <
b0 c
b0 Q
b0 Z
1*
b0 N
b0 T
b0 P
b0 M
b0 W
b0 '
b0 9
b0 :
b0 U
b1000000 F
b1000000 ]
b0 H
b0 I
14
b0 (
b0 2
b0 J
b0 B
b0 ?
b0 `
b0 G
b0 D
b0 V
b0 a
b0 @
b0 _
15
b0 &
b0 1
b0 E
b1000000 O
b0 C
b0 [
b0 b
b0 L
b0 X
b1000000 R
b111100 S
b111100 Y
b111100 ^
1!
#32
0!
#33
b1001 <
b1001 c
b100 ;
b100 d
0$
0#
1+
b100 Q
b100 Z
b100 M
b100 W
0*
b1001000000000000010000 P
b11000 =
b100 N
b100 T
b1000100 F
b1000100 ]
b100 H
b100 I
04
b100 (
b100 2
b100 J
b10010000000000000100 G
b1001 B
b11000 C
b11000 [
b11000 b
b1001 ?
b1001 `
1%
13
05
b101011 &
b101011 1
b101011 E
b1000100 O
b10101100000010010000000000000100 L
b10101100000010010000000000000100 X
b1000100 R
b1000000 S
b1000000 Y
b1000000 ^
1!
#34
0!
#35
b0 ;
b0 d
1$
1#
b0 Q
b0 Z
0+
b0 M
b0 W
b0 <
b0 c
1*
b0 N
b0 T
b0 P
b0 =
b1001000 F
b1001000 ]
b0 H
b0 I
14
b0 (
b0 2
b0 J
b0 G
b0 B
b0 C
b0 [
b0 b
b0 ?
b0 `
0%
03
15
b0 &
b0 1
b0 E
b1001000 O
b0 K
b0 \
b0 L
b0 X
b1001000 R
b1000100 S
b1000100 Y
b1000100 ^
1!
#36
0!
#37
b11000 ;
b11000 d
0#
b11000 K
b11000 \
b100 Q
b100 Z
b1111 <
b1111 c
b100 M
b100 W
b100 N
b100 T
1+
0*
b1111000000000000010000 P
b1001100 F
b1001100 ]
b100 H
b100 I
04
b100 (
b100 2
b100 J
b11110000000000000100 G
b1111 B
b1111 ?
b1111 `
1,
05
b100011 &
b100011 1
b100011 E
b1001100 O
b10001100000011110000000000000100 L
b10001100000011110000000000000100 X
b1001100 R
b1001000 S
b1001000 Y
b1001000 ^
1!
#38
0!
#39
1#
b0 K
b0 \
b0 Q
b0 Z
0+
b0 M
b0 W
b0 <
b0 c
b0 ;
b0 d
1*
b0 N
b0 T
b0 P
b1010000 F
b1010000 ]
b0 H
b0 I
14
b0 (
b0 2
b0 J
b0 G
b0 B
b0 ?
b0 `
0,
15
b0 &
b0 1
b0 E
b1010000 O
b0 C
b0 [
b0 b
b0 L
b0 X
b1010000 R
b1001100 S
b1001100 Y
b1001100 ^
1!
#40
0!
#41
0#
b11000 Q
b11000 Z
b11000 M
b11000 W
b11000 N
b11000 T
1+
0*
b1100000 P
b11111 <
b11111 c
b1010100 ;
b1010100 d
1.
b1100000 F
b1100000 ]
b11000 G
b11000 H
b11000 I
04
b11000 (
b11000 2
b11000 J
10
05
b11 &
b11 1
b11 E
b1010100 O
b1100000000000000000000011000 L
b1100000000000000000000011000 X
b1010100 R
b1010000 S
b1010000 Y
b1010000 ^
1!
#42
0!
#43
bx K
bx \
b11111111 Q
b11111111 Z
b11111111 M
b11111111 W
b1100100 F
b1100100 ]
b11111111 N
b11111111 T
b11000000000001111111100 P
b11000 <
b11000 c
0.
b11111111 H
b11111111 I
b111111 (
b111111 2
b111111 J
b11 >
b110000000000011111111 G
b11000 B
b11000 ?
b11000 `
00
b1000 &
b1000 1
b1000 E
b1100100 O
b11111111 ;
b11111111 d
b100000000110000000000011111111 L
b100000000110000000000011111111 X
b1100100 R
b1100000 S
b1100000 Y
b1100000 ^
1!
#44
0!
#45
b1010100 ;
b1010100 d
b0 K
b0 \
1.
0$
0+
b0 <
b0 c
b1010100 Q
b1010100 Z
b0 N
b0 T
b1010100 P
b1010100 M
b1010100 W
1-
b1010100 F
b1010100 ]
b1000 H
b1000 I
b1000 (
b1000 2
b1000 J
b0 >
b0 B
b0 ?
b0 `
b11111000000000000000001000 G
b1010100 D
b1010100 V
b1010100 a
b11111 @
b11111 _
15
b0 &
b0 1
b0 E
b1101000 O
b0 =
b11111000000000000000001000 L
b11111000000000000000001000 X
b1101000 R
b1100100 S
b1100100 Y
b1100100 ^
b0 C
b0 [
b0 b
1!
#46
0!
#47
b11000 <
b11000 c
b100000000 ;
b100000000 d
0.
1$
1+
b1011000 F
b1011000 ]
bx K
bx \
b100000000 Q
b100000000 Z
b11111111 =
b1 N
b1 T
b1100011000000000000000000100 P
b100000000 M
b100000000 W
0-
b1 H
b1 I
b1 (
b1 2
b1 J
b11000110000000000000000001 G
b11000 B
b11111111 C
b11111111 [
b11111111 b
b11000 ?
b11000 `
b11111111 D
b11111111 V
b11111111 a
b11000 @
b11000 _
05
b1000 &
b1000 1
b1000 E
b1011000 O
b100011000110000000000000000001 L
b100011000110000000000000000001 X
b1011000 R
b1010100 S
b1010100 Y
b1010100 ^
1!
#48
0!
#49
0$
b11010 ;
b11010 d
b0 <
b0 c
b0 K
b0 \
1.
b11010 N
b11010 T
b1101000 P
b1101000 F
b1101000 ]
b11010 Q
b11010 Z
b11010 H
b11010 I
b11010 (
b11010 2
b11010 J
b0 B
b0 ?
b0 `
b11010 G
b0 @
b0 _
16
b10 &
b10 1
b10 E
b1011100 O
b11010 M
b11010 W
b0 =
b1000000000000000000000011010 L
b1000000000000000000000011010 X
b1011100 R
b1011000 S
b1011000 Y
b1011000 ^
b0 D
b0 V
b0 a
b0 C
b0 [
b0 b
1!
#50
0!
#51
b0 ;
b0 d
1#
1$
b0 Q
b0 Z
0+
b1101100 F
b1101100 ]
b0 M
b0 W
0.
1*
b0 P
b0 N
b0 T
b0 G
b0 H
b0 I
14
b0 (
b0 2
b0 J
06
15
b0 &
b0 1
b0 E
b1101100 O
b0 L
b0 X
b1101100 R
b1101000 S
b1101000 Y
b1101000 ^
1!
#52
0!
#53
0$
b1100 ;
b1100 d
b1100 Q
b1100 Z
0#
0*
0/
b1100 =
b1100 N
b1100 T
b100101000000000000000000100 P
b1100 M
b1100 W
b1 '
b1 9
b1 :
b1 U
b1110000 F
b1110000 ]
b1 H
b1 I
04
b1 (
b1 2
b1 J
b1000 B
b1100 C
b1100 [
b1100 b
b1000 ?
b1000 `
b1001010000000000000000001 G
b11000 D
b11000 V
b11000 a
b1001 @
b1001 _
05
18
b100 &
b100 1
b100 E
b1110000 O
b10001001010000000000000000001 L
b10001001010000000000000000001 X
b1110000 R
b1101100 S
b1101100 Y
b1101100 ^
1!
#54
0!
#55
1/
b1111000 F
b1111000 ]
17
08
b101 &
b101 1
b101 E
b1111000 O
b10101001010000000000000000001 L
b10101001010000000000000000001 X
b1110100 R
b1110000 S
b1110000 Y
b1110000 ^
1!
#56
0!
#57
b1100 ;
b1100 d
b1001 <
b1001 c
b1100 Q
b1100 Z
b1100 M
b1100 W
0/
1+
b11000 =
b1100 N
b1100 T
b1001000000000000110000 P
b0 '
b0 9
b0 :
b0 U
b1111100 F
b1111100 ]
b1100 H
b1100 I
b1100 (
b1100 2
b1100 J
b1001 B
b11000 C
b11000 [
b11000 b
b1001 ?
b1001 `
b10010000000000001100 G
b0 D
b0 V
b0 a
b0 @
b0 _
1%
13
07
b101011 &
b101011 1
b101011 E
b1111100 O
b10101100000010010000000000001100 L
b10101100000010010000000000001100 X
b1111100 R
b1111000 S
b1111000 Y
b1111000 ^
1!
#58
0!
#59
b0 ;
b0 d
1$
1#
b0 Q
b0 Z
0+
b0 M
b0 W
b0 <
b0 c
1*
b0 N
b0 T
b0 P
b0 =
b10000000 F
b10000000 ]
b0 H
b0 I
14
b0 (
b0 2
b0 J
b0 G
b0 B
b0 C
b0 [
b0 b
b0 ?
b0 `
0%
03
15
b0 &
b0 1
b0 E
b10000000 O
b0 K
b0 \
b0 L
b0 X
b10000000 R
b1111100 S
b1111100 Y
b1111100 ^
1!
#60
0!
#61
x$
bx K
bx \
bx Q
bx Z
x#
x*
x+
x/
bx =
bx N
bx T
bx P
bx M
bx W
bx <
bx c
bx ;
bx d
x.
x-
bx F
bx ]
x)
x4
bx (
bx 2
bx J
bx H
bx I
bx >
bx A
bx B
bx C
bx [
bx b
bx ?
bx `
bx G
bx D
bx V
bx a
bx @
bx _
x0
x,
x6
x%
x3
x5
x7
x8
bx &
bx 1
bx E
bx O
bx L
bx X
b10000100 R
b10000000 S
b10000000 Y
b10000000 ^
1!
#62
0!
#63
bx R
bx S
bx Y
bx ^
1!
